{
    "current_program_scene": "Main Show",
    "current_scene": "Main Show",
    "current_transition": "Fade",
    "groups": [
        {
            "balance": 0.5,
            "deinterlace_field_order": 0,
            "deinterlace_mode": 0,
            "enabled": true,
            "filters": [
                {
                    "balance": 0.5,
                    "deinterlace_field_order": 0,
                    "deinterlace_mode": 0,
                    "enabled": true,
                    "flags": 0,
                    "hotkeys": {},
                    "id": "color_filter",
                    "mixers": 0,
                    "monitoring_type": 0,
                    "muted": false,
                    "name": "Colour Correction",
                    "prev_ver": 452984833,
                    "private_settings": {},
                    "push-to-mute": false,
                    "push-to-mute-delay": 0,
                    "push-to-talk": false,
                    "push-to-talk-delay": 0,
                    "settings": {
                        "brightness": -0.12759999999999999,
                        "color_add": 4284037888,
                        "contrast": 4.0,
                        "gamma": -0.62,
                        "saturation": -1.0
                    },
                    "sync": 0,
                    "versioned_id": "color_filter_v2",
                    "volume": 1.0
                }
            ],
            "flags": 0,
            "hotkeys": {
                "libobs.hide_scene_item.[internal] Zoom Call Raw": [],
                "libobs.show_scene_item.[internal] Zoom Call Raw": []
            },
            "id": "group",
            "mixers": 0,
            "monitoring_type": 0,
            "muted": false,
            "name": "Zoom Call Side FX",
            "prev_ver": 452984833,
            "private_settings": {},
            "push-to-mute": false,
            "push-to-mute-delay": 0,
            "push-to-talk": false,
            "push-to-talk-delay": 0,
            "settings": {
                "custom_size": true,
                "cx": 357,
                "cy": 800,
                "id_counter": 0,
                "items": [
                    {
                        "align": 5,
                        "bounds": {
                            "x": 0.0,
                            "y": 0.0
                        },
                        "bounds_align": 0,
                        "bounds_type": 0,
                        "crop_bottom": 0,
                        "crop_left": 0,
                        "crop_right": 969,
                        "crop_top": 0,
                        "group_item_backup": false,
                        "hide_transition": {
                            "duration": 0
                        },
                        "id": 2,
                        "locked": false,
                        "name": "[internal] Zoom Call Raw",
                        "pos": {
                            "x": 2.0,
                            "y": 397.0
                        },
                        "private_settings": {},
                        "rot": 0.0,
                        "scale": {
                            "x": 0.37329128384590149,
                            "y": 0.37314814329147339
                        },
                        "scale_filter": "disable",
                        "show_transition": {
                            "duration": 0
                        },
                        "visible": true
                    },
                    {
                        "align": 5,
                        "bounds": {
                            "x": 0.0,
                            "y": 0.0
                        },
                        "bounds_align": 0,
                        "bounds_type": 0,
                        "crop_bottom": 0,
                        "crop_left": 954,
                        "crop_right": 0,
                        "crop_top": 0,
                        "group_item_backup": false,
                        "hide_transition": {
                            "duration": 0
                        },
                        "id": 7,
                        "locked": false,
                        "name": "[internal] Zoom Call Raw",
                        "pos": {
                            "x": 0.0,
                            "y": 0.0
                        },
                        "private_settings": {},
                        "rot": 0.0,
                        "scale": {
                            "x": 0.36749482154846191,
                            "y": 0.36759260296821594
                        },
                        "scale_filter": "disable",
                        "show_transition": {
                            "duration": 0
                        },
                        "visible": true
                    }
                ]
            },
            "sync": 0,
            "versioned_id": "group",
            "volume": 1.0
        },
        {
            "balance": 0.5,
            "deinterlace_field_order": 0,
            "deinterlace_mode": 0,
            "enabled": true,
            "filters": [
                {
                    "balance": 0.5,
                    "deinterlace_field_order": 0,
                    "deinterlace_mode": 0,
                    "enabled": true,
                    "flags": 0,
                    "hotkeys": {},
                    "id": "color_filter",
                    "mixers": 0,
                    "monitoring_type": 0,
                    "muted": false,
                    "name": "Colour Correction",
                    "prev_ver": 452984833,
                    "private_settings": {},
                    "push-to-mute": false,
                    "push-to-mute-delay": 0,
                    "push-to-talk": false,
                    "push-to-talk-delay": 0,
                    "settings": {
                        "brightness": -0.025499999999999998,
                        "color_add": 4281869568,
                        "color_multiply": 4293389311,
                        "contrast": 0.34000000000000002,
                        "gamma": 0.17999999999999999,
                        "saturation": 0.080000000000000002
                    },
                    "sync": 0,
                    "versioned_id": "color_filter_v2",
                    "volume": 1.0
                }
            ],
            "flags": 0,
            "hotkeys": {
                "libobs.hide_scene_item.Pretend Zoom Call": [],
                "libobs.show_scene_item.Pretend Zoom Call": []
            },
            "id": "group",
            "mixers": 0,
            "monitoring_type": 0,
            "muted": false,
            "name": "Zoom Call",
            "prev_ver": 452984833,
            "private_settings": {},
            "push-to-mute": false,
            "push-to-mute-delay": 0,
            "push-to-talk": false,
            "push-to-talk-delay": 0,
            "settings": {
                "custom_size": true,
                "cx": 1920,
                "cy": 1080,
                "id_counter": 0,
                "items": [
                    {
                        "align": 5,
                        "bounds": {
                            "x": 0.0,
                            "y": 0.0
                        },
                        "bounds_align": 0,
                        "bounds_type": 0,
                        "crop_bottom": 0,
                        "crop_left": 0,
                        "crop_right": 0,
                        "crop_top": 0,
                        "group_item_backup": false,
                        "hide_transition": {
                            "duration": 0
                        },
                        "id": 2,
                        "locked": false,
                        "name": "Pretend Zoom Call",
                        "pos": {
                            "x": 0.0,
                            "y": 0.0
                        },
                        "private_settings": {},
                        "rot": 0.0,
                        "scale": {
                            "x": 1.5,
                            "y": 1.5
                        },
                        "scale_filter": "disable",
                        "show_transition": {
                            "duration": 0
                        },
                        "visible": true
                    }
                ]
            },
            "sync": 0,
            "versioned_id": "group",
            "volume": 1.0
        }
    ],
    "modules": {
        "auto-scene-switcher": {
            "active": false,
            "interval": 300,
            "non_matching_scene": "",
            "switch_if_not_matching": false,
            "switches": []
        },
        "captions": {
            "enabled": false,
            "lang_id": 2057,
            "provider": "mssapi",
            "source": ""
        },
        "decklink_captions": {
            "source": ""
        },
        "output-timer": {
            "autoStartRecordTimer": false,
            "autoStartStreamTimer": false,
            "pauseRecordTimer": false,
            "recordTimerHours": 0,
            "recordTimerMinutes": 0,
            "recordTimerSeconds": 0,
            "streamTimerHours": 0,
            "streamTimerMinutes": 0,
            "streamTimerSeconds": 0
        },
        "scripts-tool": []
    },
    "name": "observeress",
    "preview_locked": false,
    "quick_transitions": [
        {
            "duration": 300,
            "fade_to_black": false,
            "hotkeys": [],
            "id": 6,
            "name": "Cut"
        },
        {
            "duration": 300,
            "fade_to_black": false,
            "hotkeys": [],
            "id": 7,
            "name": "Fade"
        },
        {
            "duration": 300,
            "fade_to_black": true,
            "hotkeys": [],
            "id": 8,
            "name": "Fade"
        }
    ],
    "saved_projectors": [],
    "scaling_enabled": false,
    "scaling_level": 0,
    "scaling_off_x": 0.0,
    "scaling_off_y": 0.0,
    "scene_order": [
        {
            "name": "Blank"
        },
        {
            "name": "Countdown"
        },
        {
            "name": "Intro Video"
        },
        {
            "name": "Main Show With intro Video Music"
        },
        {
            "name": "Main Show"
        },
        {
            "name": "Main Show TL"
        },
        {
            "name": "Main Show TR"
        },
        {
            "name": "Main Show BL"
        },
        {
            "name": "Main Show BR"
        },
        {
            "name": "Media Player"
        },
        {
            "name": "[internal] Zoom Call Raw"
        },
        {
            "name": "Fullscreen Headline"
        }
    ],
    "sources": [
        {
            "balance": 0.5,
            "deinterlace_field_order": 0,
            "deinterlace_mode": 0,
            "enabled": true,
            "flags": 0,
            "hotkeys": {
                "libobs.mute": [],
                "libobs.push-to-mute": [],
                "libobs.push-to-talk": [],
                "libobs.unmute": []
            },
            "id": "browser_source",
            "mixers": 255,
            "monitoring_type": 2,
            "muted": false,
            "name": "Browser - Fullscreen Text",
            "prev_ver": 452984833,
            "private_settings": {},
            "push-to-mute": false,
            "push-to-mute-delay": 0,
            "push-to-talk": false,
            "push-to-talk-delay": 0,
            "settings": {
                "fps": 25,
                "fps_custom": true,
                "height": 1080,
                "reroute_audio": true,
                "restart_when_active": true,
                "shutdown": true,
                "url": "http://localhost:4816/display/observeress-show-demo/fullscreen-text.html",
                "width": 1920
            },
            "sync": 0,
            "versioned_id": "browser_source",
            "volume": 1.0
        },
        {
            "balance": 0.5,
            "deinterlace_field_order": 0,
            "deinterlace_mode": 0,
            "enabled": true,
            "flags": 0,
            "hotkeys": {
                "OBSBasic.SelectScene": [],
                "libobs.hide_scene_item.Browser - Fullscreen Text": [],
                "libobs.hide_scene_item.Browser - Video Background": [],
                "libobs.hide_scene_item.Main Show": [],
                "libobs.show_scene_item.Browser - Fullscreen Text": [],
                "libobs.show_scene_item.Browser - Video Background": [],
                "libobs.show_scene_item.Main Show": []
            },
            "id": "scene",
            "mixers": 0,
            "monitoring_type": 0,
            "muted": false,
            "name": "Fullscreen Headline",
            "prev_ver": 452984833,
            "private_settings": {},
            "push-to-mute": false,
            "push-to-mute-delay": 0,
            "push-to-talk": false,
            "push-to-talk-delay": 0,
            "settings": {
                "custom_size": false,
                "id_counter": 3,
                "items": [
                    {
                        "align": 5,
                        "bounds": {
                            "x": 0.0,
                            "y": 0.0
                        },
                        "bounds_align": 0,
                        "bounds_type": 0,
                        "crop_bottom": 0,
                        "crop_left": 0,
                        "crop_right": 0,
                        "crop_top": 0,
                        "group_item_backup": false,
                        "hide_transition": {
                            "duration": 0
                        },
                        "id": 1,
                        "locked": false,
                        "name": "Main Show",
                        "pos": {
                            "x": 0.0,
                            "y": 0.0
                        },
                        "private_settings": {},
                        "rot": 0.0,
                        "scale": {
                            "x": 1.0,
                            "y": 1.0
                        },
                        "scale_filter": "disable",
                        "show_transition": {
                            "duration": 0
                        },
                        "visible": true
                    },
                    {
                        "align": 5,
                        "bounds": {
                            "x": 0.0,
                            "y": 0.0
                        },
                        "bounds_align": 0,
                        "bounds_type": 0,
                        "crop_bottom": 0,
                        "crop_left": 0,
                        "crop_right": 0,
                        "crop_top": 0,
                        "group_item_backup": false,
                        "hide_transition": {
                            "duration": 0
                        },
                        "id": 2,
                        "locked": false,
                        "name": "Browser - Fullscreen Text",
                        "pos": {
                            "x": 0.0,
                            "y": 0.0
                        },
                        "private_settings": {},
                        "rot": 0.0,
                        "scale": {
                            "x": 1.0,
                            "y": 1.0
                        },
                        "scale_filter": "disable",
                        "show_transition": {
                            "duration": 0
                        },
                        "visible": true
                    },
                    {
                        "align": 5,
                        "bounds": {
                            "x": 0.0,
                            "y": 0.0
                        },
                        "bounds_align": 0,
                        "bounds_type": 0,
                        "crop_bottom": 0,
                        "crop_left": 0,
                        "crop_right": 0,
                        "crop_top": 0,
                        "group_item_backup": false,
                        "hide_transition": {
                            "duration": 0
                        },
                        "id": 3,
                        "locked": false,
                        "name": "Browser - Video Background",
                        "pos": {
                            "x": 0.0,
                            "y": 0.0
                        },
                        "private_settings": {},
                        "rot": 0.0,
                        "scale": {
                            "x": 1.0,
                            "y": 1.0
                        },
                        "scale_filter": "disable",
                        "show_transition": {
                            "duration": 0
                        },
                        "visible": true
                    }
                ]
            },
            "sync": 0,
            "versioned_id": "scene",
            "volume": 1.0
        },
        {
            "balance": 0.5,
            "deinterlace_field_order": 0,
            "deinterlace_mode": 0,
            "enabled": true,
            "flags": 0,
            "hotkeys": {
                "libobs.mute": [],
                "libobs.push-to-mute": [],
                "libobs.push-to-talk": [],
                "libobs.unmute": []
            },
            "id": "wasapi_input_capture",
            "mixers": 255,
            "monitoring_type": 0,
            "muted": false,
            "name": "Zoom Audio",
            "prev_ver": 452984833,
            "private_settings": {},
            "push-to-mute": false,
            "push-to-mute-delay": 0,
            "push-to-talk": false,
            "push-to-talk-delay": 0,
            "settings": {
                "device_id": "{0.0.1.00000000}.{9b60d466-8eb3-4b14-b299-d7c4a21f9831}"
            },
            "sync": 0,
            "versioned_id": "wasapi_input_capture",
            "volume": 1.0
        },
        {
            "balance": 0.5,
            "deinterlace_field_order": 0,
            "deinterlace_mode": 0,
            "enabled": true,
            "flags": 0,
            "hotkeys": {
                "OBSBasic.SelectScene": [],
                "libobs.hide_scene_item.Browser - Main Footer": [],
                "libobs.hide_scene_item.Browser - Main Zoom Surround": [],
                "libobs.hide_scene_item.Browser - Video Background": [],
                "libobs.hide_scene_item.Zoom Audio": [],
                "libobs.hide_scene_item.[internal] Zoom Call Raw": [],
                "libobs.show_scene_item.Browser - Main Footer": [],
                "libobs.show_scene_item.Browser - Main Zoom Surround": [],
                "libobs.show_scene_item.Browser - Video Background": [],
                "libobs.show_scene_item.Zoom Audio": [],
                "libobs.show_scene_item.[internal] Zoom Call Raw": []
            },
            "id": "scene",
            "mixers": 0,
            "monitoring_type": 0,
            "muted": false,
            "name": "Main Show BR",
            "prev_ver": 452984833,
            "private_settings": {},
            "push-to-mute": false,
            "push-to-mute-delay": 0,
            "push-to-talk": false,
            "push-to-talk-delay": 0,
            "settings": {
                "custom_size": false,
                "id_counter": 5,
                "items": [
                    {
                        "align": 5,
                        "bounds": {
                            "x": 0.0,
                            "y": 0.0
                        },
                        "bounds_align": 0,
                        "bounds_type": 0,
                        "crop_bottom": 0,
                        "crop_left": 0,
                        "crop_right": 0,
                        "crop_top": 0,
                        "group_item_backup": false,
                        "hide_transition": {
                            "duration": 0
                        },
                        "id": 1,
                        "locked": false,
                        "name": "Browser - Video Background",
                        "pos": {
                            "x": 0.0,
                            "y": 0.0
                        },
                        "private_settings": {},
                        "rot": 0.0,
                        "scale": {
                            "x": 1.0,
                            "y": 1.0
                        },
                        "scale_filter": "disable",
                        "show_transition": {
                            "duration": 0
                        },
                        "visible": true
                    },
                    {
                        "align": 5,
                        "bounds": {
                            "x": 0.0,
                            "y": 0.0
                        },
                        "bounds_align": 0,
                        "bounds_type": 0,
                        "crop_bottom": 0,
                        "crop_left": 963,
                        "crop_right": 0,
                        "crop_top": 544,
                        "group_item_backup": false,
                        "hide_transition": {
                            "duration": 0
                        },
                        "id": 2,
                        "locked": false,
                        "name": "[internal] Zoom Call Raw",
                        "pos": {
                            "x": 248.0,
                            "y": 36.0
                        },
                        "private_settings": {},
                        "rot": 0.0,
                        "scale": {
                            "x": 1.4890282154083252,
                            "y": 1.4880294799804688
                        },
                        "scale_filter": "disable",
                        "show_transition": {
                            "duration": 0
                        },
                        "visible": true
                    },
                    {
                        "align": 5,
                        "bounds": {
                            "x": 0.0,
                            "y": 0.0
                        },
                        "bounds_align": 0,
                        "bounds_type": 0,
                        "crop_bottom": 0,
                        "crop_left": 0,
                        "crop_right": 0,
                        "crop_top": 0,
                        "group_item_backup": false,
                        "hide_transition": {
                            "duration": 0
                        },
                        "id": 3,
                        "locked": false,
                        "name": "Browser - Main Footer",
                        "pos": {
                            "x": 0.0,
                            "y": 0.0
                        },
                        "private_settings": {},
                        "rot": 0.0,
                        "scale": {
                            "x": 1.0,
                            "y": 1.0
                        },
                        "scale_filter": "disable",
                        "show_transition": {
                            "duration": 0
                        },
                        "visible": true
                    },
                    {
                        "align": 5,
                        "bounds": {
                            "x": 0.0,
                            "y": 0.0
                        },
                        "bounds_align": 0,
                        "bounds_type": 0,
                        "crop_bottom": 0,
                        "crop_left": 0,
                        "crop_right": 0,
                        "crop_top": 0,
                        "group_item_backup": false,
                        "hide_transition": {
                            "duration": 0
                        },
                        "id": 4,
                        "locked": false,
                        "name": "Zoom Audio",
                        "pos": {
                            "x": 0.0,
                            "y": 0.0
                        },
                        "private_settings": {},
                        "rot": 0.0,
                        "scale": {
                            "x": 1.0,
                            "y": 1.0
                        },
                        "scale_filter": "disable",
                        "show_transition": {
                            "duration": 0
                        },
                        "visible": true
                    },
                    {
                        "align": 5,
                        "bounds": {
                            "x": 0.0,
                            "y": 0.0
                        },
                        "bounds_align": 0,
                        "bounds_type": 0,
                        "crop_bottom": 210,
                        "crop_left": 0,
                        "crop_right": 0,
                        "crop_top": 0,
                        "group_item_backup": false,
                        "hide_transition": {
                            "duration": 0
                        },
                        "id": 5,
                        "locked": false,
                        "name": "Browser - Main Zoom Surround",
                        "pos": {
                            "x": 0.0,
                            "y": 0.0
                        },
                        "private_settings": {},
                        "rot": 0.0,
                        "scale": {
                            "x": 1.0,
                            "y": 1.0
                        },
                        "scale_filter": "disable",
                        "show_transition": {
                            "duration": 0
                        },
                        "visible": true
                    }
                ]
            },
            "sync": 0,
            "versioned_id": "scene",
            "volume": 1.0
        },
        {
            "balance": 0.5,
            "deinterlace_field_order": 0,
            "deinterlace_mode": 0,
            "enabled": true,
            "flags": 0,
            "hotkeys": {
                "OBSBasic.SelectScene": [],
                "libobs.hide_scene_item.Browser - Main Footer": [],
                "libobs.hide_scene_item.Browser - Main Zoom Surround": [],
                "libobs.hide_scene_item.Browser - Video Background": [],
                "libobs.hide_scene_item.Zoom Audio": [],
                "libobs.hide_scene_item.[internal] Zoom Call Raw": [],
                "libobs.show_scene_item.Browser - Main Footer": [],
                "libobs.show_scene_item.Browser - Main Zoom Surround": [],
                "libobs.show_scene_item.Browser - Video Background": [],
                "libobs.show_scene_item.Zoom Audio": [],
                "libobs.show_scene_item.[internal] Zoom Call Raw": []
            },
            "id": "scene",
            "mixers": 0,
            "monitoring_type": 0,
            "muted": false,
            "name": "Main Show BL",
            "prev_ver": 452984833,
            "private_settings": {},
            "push-to-mute": false,
            "push-to-mute-delay": 0,
            "push-to-talk": false,
            "push-to-talk-delay": 0,
            "settings": {
                "custom_size": false,
                "id_counter": 5,
                "items": [
                    {
                        "align": 5,
                        "bounds": {
                            "x": 0.0,
                            "y": 0.0
                        },
                        "bounds_align": 0,
                        "bounds_type": 0,
                        "crop_bottom": 0,
                        "crop_left": 0,
                        "crop_right": 0,
                        "crop_top": 0,
                        "group_item_backup": false,
                        "hide_transition": {
                            "duration": 0
                        },
                        "id": 1,
                        "locked": false,
                        "name": "Browser - Video Background",
                        "pos": {
                            "x": 0.0,
                            "y": 0.0
                        },
                        "private_settings": {},
                        "rot": 0.0,
                        "scale": {
                            "x": 1.0,
                            "y": 1.0
                        },
                        "scale_filter": "disable",
                        "show_transition": {
                            "duration": 0
                        },
                        "visible": true
                    },
                    {
                        "align": 5,
                        "bounds": {
                            "x": 0.0,
                            "y": 0.0
                        },
                        "bounds_align": 0,
                        "bounds_type": 0,
                        "crop_bottom": 0,
                        "crop_left": 0,
                        "crop_right": 964,
                        "crop_top": 544,
                        "group_item_backup": false,
                        "hide_transition": {
                            "duration": 0
                        },
                        "id": 2,
                        "locked": false,
                        "name": "[internal] Zoom Call Raw",
                        "pos": {
                            "x": 247.0,
                            "y": 33.0
                        },
                        "private_settings": {},
                        "rot": 0.0,
                        "scale": {
                            "x": 1.4937238693237305,
                            "y": 1.4944444894790649
                        },
                        "scale_filter": "disable",
                        "show_transition": {
                            "duration": 0
                        },
                        "visible": true
                    },
                    {
                        "align": 5,
                        "bounds": {
                            "x": 0.0,
                            "y": 0.0
                        },
                        "bounds_align": 0,
                        "bounds_type": 0,
                        "crop_bottom": 0,
                        "crop_left": 0,
                        "crop_right": 0,
                        "crop_top": 0,
                        "group_item_backup": false,
                        "hide_transition": {
                            "duration": 0
                        },
                        "id": 3,
                        "locked": false,
                        "name": "Browser - Main Footer",
                        "pos": {
                            "x": 0.0,
                            "y": 0.0
                        },
                        "private_settings": {},
                        "rot": 0.0,
                        "scale": {
                            "x": 1.0,
                            "y": 1.0
                        },
                        "scale_filter": "disable",
                        "show_transition": {
                            "duration": 0
                        },
                        "visible": true
                    },
                    {
                        "align": 5,
                        "bounds": {
                            "x": 0.0,
                            "y": 0.0
                        },
                        "bounds_align": 0,
                        "bounds_type": 0,
                        "crop_bottom": 0,
                        "crop_left": 0,
                        "crop_right": 0,
                        "crop_top": 0,
                        "group_item_backup": false,
                        "hide_transition": {
                            "duration": 0
                        },
                        "id": 4,
                        "locked": false,
                        "name": "Zoom Audio",
                        "pos": {
                            "x": 0.0,
                            "y": 0.0
                        },
                        "private_settings": {},
                        "rot": 0.0,
                        "scale": {
                            "x": 1.0,
                            "y": 1.0
                        },
                        "scale_filter": "disable",
                        "show_transition": {
                            "duration": 0
                        },
                        "visible": true
                    },
                    {
                        "align": 5,
                        "bounds": {
                            "x": 0.0,
                            "y": 0.0
                        },
                        "bounds_align": 0,
                        "bounds_type": 0,
                        "crop_bottom": 219,
                        "crop_left": 0,
                        "crop_right": 0,
                        "crop_top": 0,
                        "group_item_backup": false,
                        "hide_transition": {
                            "duration": 0
                        },
                        "id": 5,
                        "locked": false,
                        "name": "Browser - Main Zoom Surround",
                        "pos": {
                            "x": 0.0,
                            "y": 0.0
                        },
                        "private_settings": {},
                        "rot": 0.0,
                        "scale": {
                            "x": 1.0,
                            "y": 1.0
                        },
                        "scale_filter": "disable",
                        "show_transition": {
                            "duration": 0
                        },
                        "visible": true
                    }
                ]
            },
            "sync": 0,
            "versioned_id": "scene",
            "volume": 1.0
        },
        {
            "balance": 0.5,
            "deinterlace_field_order": 0,
            "deinterlace_mode": 0,
            "enabled": true,
            "flags": 0,
            "hotkeys": {
                "OBSBasic.SelectScene": [],
                "libobs.hide_scene_item.Browser - Main Footer": [],
                "libobs.hide_scene_item.Browser - Main Zoom Surround": [],
                "libobs.hide_scene_item.Browser - Video Background": [],
                "libobs.hide_scene_item.Zoom Audio": [],
                "libobs.hide_scene_item.[internal] Zoom Call Raw": [],
                "libobs.show_scene_item.Browser - Main Footer": [],
                "libobs.show_scene_item.Browser - Main Zoom Surround": [],
                "libobs.show_scene_item.Browser - Video Background": [],
                "libobs.show_scene_item.Zoom Audio": [],
                "libobs.show_scene_item.[internal] Zoom Call Raw": []
            },
            "id": "scene",
            "mixers": 0,
            "monitoring_type": 0,
            "muted": false,
            "name": "Main Show TR",
            "prev_ver": 452984833,
            "private_settings": {},
            "push-to-mute": false,
            "push-to-mute-delay": 0,
            "push-to-talk": false,
            "push-to-talk-delay": 0,
            "settings": {
                "custom_size": false,
                "id_counter": 5,
                "items": [
                    {
                        "align": 5,
                        "bounds": {
                            "x": 0.0,
                            "y": 0.0
                        },
                        "bounds_align": 0,
                        "bounds_type": 0,
                        "crop_bottom": 0,
                        "crop_left": 0,
                        "crop_right": 0,
                        "crop_top": 0,
                        "group_item_backup": false,
                        "hide_transition": {
                            "duration": 0
                        },
                        "id": 1,
                        "locked": false,
                        "name": "Browser - Video Background",
                        "pos": {
                            "x": 0.0,
                            "y": 0.0
                        },
                        "private_settings": {},
                        "rot": 0.0,
                        "scale": {
                            "x": 1.0,
                            "y": 1.0
                        },
                        "scale_filter": "disable",
                        "show_transition": {
                            "duration": 0
                        },
                        "visible": true
                    },
                    {
                        "align": 5,
                        "bounds": {
                            "x": 0.0,
                            "y": 0.0
                        },
                        "bounds_align": 0,
                        "bounds_type": 0,
                        "crop_bottom": 543,
                        "crop_left": 968,
                        "crop_right": 0,
                        "crop_top": 0,
                        "group_item_backup": false,
                        "hide_transition": {
                            "duration": 0
                        },
                        "id": 2,
                        "locked": false,
                        "name": "[internal] Zoom Call Raw",
                        "pos": {
                            "x": 246.0,
                            "y": 32.0
                        },
                        "private_settings": {},
                        "rot": 0.0,
                        "scale": {
                            "x": 1.4989495277404785,
                            "y": 1.4990688562393188
                        },
                        "scale_filter": "disable",
                        "show_transition": {
                            "duration": 0
                        },
                        "visible": true
                    },
                    {
                        "align": 5,
                        "bounds": {
                            "x": 0.0,
                            "y": 0.0
                        },
                        "bounds_align": 0,
                        "bounds_type": 0,
                        "crop_bottom": 0,
                        "crop_left": 0,
                        "crop_right": 0,
                        "crop_top": 0,
                        "group_item_backup": false,
                        "hide_transition": {
                            "duration": 0
                        },
                        "id": 3,
                        "locked": false,
                        "name": "Browser - Main Footer",
                        "pos": {
                            "x": 0.0,
                            "y": 0.0
                        },
                        "private_settings": {},
                        "rot": 0.0,
                        "scale": {
                            "x": 1.0,
                            "y": 1.0
                        },
                        "scale_filter": "disable",
                        "show_transition": {
                            "duration": 0
                        },
                        "visible": true
                    },
                    {
                        "align": 5,
                        "bounds": {
                            "x": 0.0,
                            "y": 0.0
                        },
                        "bounds_align": 0,
                        "bounds_type": 0,
                        "crop_bottom": 0,
                        "crop_left": 0,
                        "crop_right": 0,
                        "crop_top": 0,
                        "group_item_backup": false,
                        "hide_transition": {
                            "duration": 0
                        },
                        "id": 4,
                        "locked": false,
                        "name": "Zoom Audio",
                        "pos": {
                            "x": 0.0,
                            "y": 0.0
                        },
                        "private_settings": {},
                        "rot": 0.0,
                        "scale": {
                            "x": 1.0,
                            "y": 1.0
                        },
                        "scale_filter": "disable",
                        "show_transition": {
                            "duration": 0
                        },
                        "visible": true
                    },
                    {
                        "align": 5,
                        "bounds": {
                            "x": 0.0,
                            "y": 0.0
                        },
                        "bounds_align": 0,
                        "bounds_type": 0,
                        "crop_bottom": 213,
                        "crop_left": 0,
                        "crop_right": 0,
                        "crop_top": 0,
                        "group_item_backup": false,
                        "hide_transition": {
                            "duration": 0
                        },
                        "id": 5,
                        "locked": false,
                        "name": "Browser - Main Zoom Surround",
                        "pos": {
                            "x": 0.0,
                            "y": 0.0
                        },
                        "private_settings": {},
                        "rot": 0.0,
                        "scale": {
                            "x": 1.0,
                            "y": 1.0
                        },
                        "scale_filter": "disable",
                        "show_transition": {
                            "duration": 0
                        },
                        "visible": true
                    }
                ]
            },
            "sync": 0,
            "versioned_id": "scene",
            "volume": 1.0
        },
        {
            "balance": 0.5,
            "deinterlace_field_order": 0,
            "deinterlace_mode": 0,
            "enabled": true,
            "flags": 0,
            "hotkeys": {
                "OBSBasic.SelectScene": [],
                "libobs.hide_scene_item.Browser - Main Footer": [],
                "libobs.hide_scene_item.Browser - Main Zoom Surround": [],
                "libobs.hide_scene_item.Browser - Video Background": [],
                "libobs.hide_scene_item.Zoom Audio": [],
                "libobs.hide_scene_item.[internal] Zoom Call Raw": [],
                "libobs.show_scene_item.Browser - Main Footer": [],
                "libobs.show_scene_item.Browser - Main Zoom Surround": [],
                "libobs.show_scene_item.Browser - Video Background": [],
                "libobs.show_scene_item.Zoom Audio": [],
                "libobs.show_scene_item.[internal] Zoom Call Raw": []
            },
            "id": "scene",
            "mixers": 0,
            "monitoring_type": 0,
            "muted": false,
            "name": "Main Show TL",
            "prev_ver": 452984833,
            "private_settings": {},
            "push-to-mute": false,
            "push-to-mute-delay": 0,
            "push-to-talk": false,
            "push-to-talk-delay": 0,
            "settings": {
                "custom_size": false,
                "id_counter": 5,
                "items": [
                    {
                        "align": 5,
                        "bounds": {
                            "x": 0.0,
                            "y": 0.0
                        },
                        "bounds_align": 0,
                        "bounds_type": 0,
                        "crop_bottom": 0,
                        "crop_left": 0,
                        "crop_right": 0,
                        "crop_top": 0,
                        "group_item_backup": false,
                        "hide_transition": {
                            "duration": 0
                        },
                        "id": 1,
                        "locked": false,
                        "name": "Browser - Video Background",
                        "pos": {
                            "x": 0.0,
                            "y": 0.0
                        },
                        "private_settings": {},
                        "rot": 0.0,
                        "scale": {
                            "x": 1.0,
                            "y": 1.0
                        },
                        "scale_filter": "disable",
                        "show_transition": {
                            "duration": 0
                        },
                        "visible": true
                    },
                    {
                        "align": 5,
                        "bounds": {
                            "x": 0.0,
                            "y": 0.0
                        },
                        "bounds_align": 0,
                        "bounds_type": 0,
                        "crop_bottom": 551,
                        "crop_left": 0,
                        "crop_right": 976,
                        "crop_top": 0,
                        "group_item_backup": false,
                        "hide_transition": {
                            "duration": 0
                        },
                        "id": 2,
                        "locked": false,
                        "name": "[internal] Zoom Call Raw",
                        "pos": {
                            "x": 247.0,
                            "y": 32.0
                        },
                        "private_settings": {},
                        "rot": 0.0,
                        "scale": {
                            "x": 1.5131164789199829,
                            "y": 1.5122873783111572
                        },
                        "scale_filter": "disable",
                        "show_transition": {
                            "duration": 0
                        },
                        "visible": true
                    },
                    {
                        "align": 5,
                        "bounds": {
                            "x": 0.0,
                            "y": 0.0
                        },
                        "bounds_align": 0,
                        "bounds_type": 0,
                        "crop_bottom": 0,
                        "crop_left": 0,
                        "crop_right": 0,
                        "crop_top": 0,
                        "group_item_backup": false,
                        "hide_transition": {
                            "duration": 0
                        },
                        "id": 3,
                        "locked": false,
                        "name": "Browser - Main Footer",
                        "pos": {
                            "x": 0.0,
                            "y": 0.0
                        },
                        "private_settings": {},
                        "rot": 0.0,
                        "scale": {
                            "x": 1.0,
                            "y": 1.0
                        },
                        "scale_filter": "disable",
                        "show_transition": {
                            "duration": 0
                        },
                        "visible": true
                    },
                    {
                        "align": 5,
                        "bounds": {
                            "x": 0.0,
                            "y": 0.0
                        },
                        "bounds_align": 0,
                        "bounds_type": 0,
                        "crop_bottom": 0,
                        "crop_left": 0,
                        "crop_right": 0,
                        "crop_top": 0,
                        "group_item_backup": false,
                        "hide_transition": {
                            "duration": 0
                        },
                        "id": 4,
                        "locked": false,
                        "name": "Zoom Audio",
                        "pos": {
                            "x": 0.0,
                            "y": 0.0
                        },
                        "private_settings": {},
                        "rot": 0.0,
                        "scale": {
                            "x": 1.0,
                            "y": 1.0
                        },
                        "scale_filter": "disable",
                        "show_transition": {
                            "duration": 0
                        },
                        "visible": true
                    },
                    {
                        "align": 5,
                        "bounds": {
                            "x": 0.0,
                            "y": 0.0
                        },
                        "bounds_align": 0,
                        "bounds_type": 0,
                        "crop_bottom": 216,
                        "crop_left": 0,
                        "crop_right": 0,
                        "crop_top": 0,
                        "group_item_backup": false,
                        "hide_transition": {
                            "duration": 0
                        },
                        "id": 5,
                        "locked": false,
                        "name": "Browser - Main Zoom Surround",
                        "pos": {
                            "x": 0.0,
                            "y": 0.0
                        },
                        "private_settings": {},
                        "rot": 0.0,
                        "scale": {
                            "x": 1.0,
                            "y": 1.0
                        },
                        "scale_filter": "disable",
                        "show_transition": {
                            "duration": 0
                        },
                        "visible": true
                    }
                ]
            },
            "sync": 0,
            "versioned_id": "scene",
            "volume": 1.0
        },
        {
            "balance": 0.5,
            "deinterlace_field_order": 0,
            "deinterlace_mode": 0,
            "enabled": true,
            "flags": 0,
            "hotkeys": {
                "libobs.mute": [],
                "libobs.push-to-mute": [],
                "libobs.push-to-talk": [],
                "libobs.unmute": []
            },
            "id": "browser_source",
            "mixers": 255,
            "monitoring_type": 0,
            "muted": false,
            "name": "Browser - Video Background",
            "prev_ver": 452984833,
            "private_settings": {},
            "push-to-mute": false,
            "push-to-mute-delay": 0,
            "push-to-talk": false,
            "push-to-talk-delay": 0,
            "settings": {
                "height": 1080,
                "url": "http://localhost:4816/display/observeress-show-demo/video-background.html",
                "width": 1920
            },
            "sync": 0,
            "versioned_id": "browser_source",
            "volume": 1.0
        },
        {
            "balance": 0.5,
            "deinterlace_field_order": 0,
            "deinterlace_mode": 0,
            "enabled": true,
            "flags": 0,
            "hotkeys": {
                "libobs.mute": [],
                "libobs.push-to-mute": [],
                "libobs.push-to-talk": [],
                "libobs.unmute": []
            },
            "id": "browser_source",
            "mixers": 255,
            "monitoring_type": 0,
            "muted": false,
            "name": "Browser - Main Footer",
            "prev_ver": 452984833,
            "private_settings": {},
            "push-to-mute": false,
            "push-to-mute-delay": 0,
            "push-to-talk": false,
            "push-to-talk-delay": 0,
            "settings": {
                "height": 1080,
                "reroute_audio": true,
                "url": "http://localhost:4816/display/observeress-show-demo/main-footer.html",
                "width": 1920
            },
            "sync": 0,
            "versioned_id": "browser_source",
            "volume": 1.0
        },
        {
            "balance": 0.5,
            "deinterlace_field_order": 0,
            "deinterlace_mode": 0,
            "enabled": true,
            "flags": 0,
            "hotkeys": {
                "OBSBasic.SelectScene": [],
                "libobs.hide_scene_item.Main Show": [],
                "libobs.hide_scene_item.Media Source - Intro Video": [],
                "libobs.hide_scene_item.Zoom Audio": [],
                "libobs.show_scene_item.Main Show": [],
                "libobs.show_scene_item.Media Source - Intro Video": [],
                "libobs.show_scene_item.Zoom Audio": []
            },
            "id": "scene",
            "mixers": 0,
            "monitoring_type": 0,
            "muted": false,
            "name": "Main Show With intro Video Music",
            "prev_ver": 452984833,
            "private_settings": {},
            "push-to-mute": false,
            "push-to-mute-delay": 0,
            "push-to-talk": false,
            "push-to-talk-delay": 0,
            "settings": {
                "custom_size": false,
                "id_counter": 3,
                "items": [
                    {
                        "align": 5,
                        "bounds": {
                            "x": 0.0,
                            "y": 0.0
                        },
                        "bounds_align": 0,
                        "bounds_type": 0,
                        "crop_bottom": 0,
                        "crop_left": 0,
                        "crop_right": 0,
                        "crop_top": 1078,
                        "group_item_backup": false,
                        "hide_transition": {
                            "duration": 0
                        },
                        "id": 1,
                        "locked": false,
                        "name": "Media Source - Intro Video",
                        "pos": {
                            "x": 0.0,
                            "y": 1078.0
                        },
                        "private_settings": {},
                        "rot": 0.0,
                        "scale": {
                            "x": 1.0,
                            "y": 1.0
                        },
                        "scale_filter": "disable",
                        "show_transition": {
                            "duration": 0
                        },
                        "visible": true
                    },
                    {
                        "align": 5,
                        "bounds": {
                            "x": 0.0,
                            "y": 0.0
                        },
                        "bounds_align": 0,
                        "bounds_type": 0,
                        "crop_bottom": 0,
                        "crop_left": 0,
                        "crop_right": 0,
                        "crop_top": 0,
                        "group_item_backup": false,
                        "hide_transition": {
                            "duration": 0
                        },
                        "id": 2,
                        "locked": false,
                        "name": "Main Show",
                        "pos": {
                            "x": 0.0,
                            "y": 0.0
                        },
                        "private_settings": {},
                        "rot": 0.0,
                        "scale": {
                            "x": 1.0,
                            "y": 1.0
                        },
                        "scale_filter": "disable",
                        "show_transition": {
                            "duration": 0
                        },
                        "visible": true
                    },
                    {
                        "align": 5,
                        "bounds": {
                            "x": 0.0,
                            "y": 0.0
                        },
                        "bounds_align": 0,
                        "bounds_type": 0,
                        "crop_bottom": 0,
                        "crop_left": 0,
                        "crop_right": 0,
                        "crop_top": 0,
                        "group_item_backup": false,
                        "hide_transition": {
                            "duration": 0
                        },
                        "id": 3,
                        "locked": false,
                        "name": "Zoom Audio",
                        "pos": {
                            "x": 0.0,
                            "y": 0.0
                        },
                        "private_settings": {},
                        "rot": 0.0,
                        "scale": {
                            "x": 1.0,
                            "y": 1.0
                        },
                        "scale_filter": "disable",
                        "show_transition": {
                            "duration": 0
                        },
                        "visible": true
                    }
                ]
            },
            "sync": 0,
            "versioned_id": "scene",
            "volume": 1.0
        },
        {
            "balance": 0.5,
            "deinterlace_field_order": 0,
            "deinterlace_mode": 0,
            "enabled": true,
            "flags": 0,
            "hotkeys": {
                "OBSBasic.SelectScene": [],
                "libobs.hide_scene_item.Browser - Main Footer": [],
                "libobs.hide_scene_item.Browser - Main Zoom Surround": [],
                "libobs.hide_scene_item.Browser - Video Background": [],
                "libobs.hide_scene_item.Zoom Audio": [],
                "libobs.hide_scene_item.[internal] Zoom Call Raw": [],
                "libobs.show_scene_item.Browser - Main Footer": [],
                "libobs.show_scene_item.Browser - Main Zoom Surround": [],
                "libobs.show_scene_item.Browser - Video Background": [],
                "libobs.show_scene_item.Zoom Audio": [],
                "libobs.show_scene_item.[internal] Zoom Call Raw": []
            },
            "id": "scene",
            "mixers": 0,
            "monitoring_type": 0,
            "muted": false,
            "name": "Main Show",
            "prev_ver": 452984833,
            "private_settings": {},
            "push-to-mute": false,
            "push-to-mute-delay": 0,
            "push-to-talk": false,
            "push-to-talk-delay": 0,
            "settings": {
                "custom_size": false,
                "id_counter": 6,
                "items": [
                    {
                        "align": 5,
                        "bounds": {
                            "x": 0.0,
                            "y": 0.0
                        },
                        "bounds_align": 0,
                        "bounds_type": 0,
                        "crop_bottom": 0,
                        "crop_left": 0,
                        "crop_right": 0,
                        "crop_top": 0,
                        "group_item_backup": false,
                        "hide_transition": {
                            "duration": 0
                        },
                        "id": 4,
                        "locked": false,
                        "name": "Browser - Video Background",
                        "pos": {
                            "x": 0.0,
                            "y": 0.0
                        },
                        "private_settings": {},
                        "rot": 0.0,
                        "scale": {
                            "x": 1.0,
                            "y": 1.0
                        },
                        "scale_filter": "disable",
                        "show_transition": {
                            "duration": 0
                        },
                        "visible": true
                    },
                    {
                        "align": 5,
                        "bounds": {
                            "x": 0.0,
                            "y": 0.0
                        },
                        "bounds_align": 0,
                        "bounds_type": 0,
                        "crop_bottom": 0,
                        "crop_left": 0,
                        "crop_right": 0,
                        "crop_top": 0,
                        "group_item_backup": false,
                        "hide_transition": {
                            "duration": 0
                        },
                        "id": 3,
                        "locked": false,
                        "name": "[internal] Zoom Call Raw",
                        "pos": {
                            "x": 247.0,
                            "y": 32.0
                        },
                        "private_settings": {},
                        "rot": 0.0,
                        "scale": {
                            "x": 0.74270832538604736,
                            "y": 0.74259257316589355
                        },
                        "scale_filter": "disable",
                        "show_transition": {
                            "duration": 0
                        },
                        "visible": true
                    },
                    {
                        "align": 5,
                        "bounds": {
                            "x": 0.0,
                            "y": 0.0
                        },
                        "bounds_align": 0,
                        "bounds_type": 0,
                        "crop_bottom": 0,
                        "crop_left": 0,
                        "crop_right": 0,
                        "crop_top": 0,
                        "group_item_backup": false,
                        "hide_transition": {
                            "duration": 0
                        },
                        "id": 2,
                        "locked": false,
                        "name": "Browser - Main Footer",
                        "pos": {
                            "x": 0.0,
                            "y": 0.0
                        },
                        "private_settings": {},
                        "rot": 0.0,
                        "scale": {
                            "x": 1.0,
                            "y": 1.0
                        },
                        "scale_filter": "disable",
                        "show_transition": {
                            "duration": 0
                        },
                        "visible": true
                    },
                    {
                        "align": 5,
                        "bounds": {
                            "x": 0.0,
                            "y": 0.0
                        },
                        "bounds_align": 0,
                        "bounds_type": 0,
                        "crop_bottom": 215,
                        "crop_left": 0,
                        "crop_right": 0,
                        "crop_top": 0,
                        "group_item_backup": false,
                        "hide_transition": {
                            "duration": 0
                        },
                        "id": 6,
                        "locked": false,
                        "name": "Browser - Main Zoom Surround",
                        "pos": {
                            "x": 0.0,
                            "y": 0.0
                        },
                        "private_settings": {},
                        "rot": 0.0,
                        "scale": {
                            "x": 1.0,
                            "y": 1.0
                        },
                        "scale_filter": "disable",
                        "show_transition": {
                            "duration": 0
                        },
                        "visible": true
                    },
                    {
                        "align": 5,
                        "bounds": {
                            "x": 0.0,
                            "y": 0.0
                        },
                        "bounds_align": 0,
                        "bounds_type": 0,
                        "crop_bottom": 0,
                        "crop_left": 0,
                        "crop_right": 0,
                        "crop_top": 0,
                        "group_item_backup": false,
                        "hide_transition": {
                            "duration": 0
                        },
                        "id": 5,
                        "locked": false,
                        "name": "Zoom Audio",
                        "pos": {
                            "x": 0.0,
                            "y": 0.0
                        },
                        "private_settings": {},
                        "rot": 0.0,
                        "scale": {
                            "x": 1.0,
                            "y": 1.0
                        },
                        "scale_filter": "disable",
                        "show_transition": {
                            "duration": 0
                        },
                        "visible": true
                    }
                ]
            },
            "sync": 0,
            "versioned_id": "scene",
            "volume": 1.0
        },
        {
            "balance": 0.5,
            "deinterlace_field_order": 0,
            "deinterlace_mode": 0,
            "enabled": true,
            "flags": 0,
            "hotkeys": {
                "MediaSource.Pause": [],
                "MediaSource.Play": [],
                "MediaSource.Restart": [],
                "MediaSource.Stop": [],
                "libobs.mute": [],
                "libobs.push-to-mute": [],
                "libobs.push-to-talk": [],
                "libobs.unmute": []
            },
            "id": "ffmpeg_source",
            "mixers": 255,
            "monitoring_type": 2,
            "muted": false,
            "name": "Media Source - Intro Video",
            "prev_ver": 452984833,
            "private_settings": {},
            "push-to-mute": false,
            "push-to-mute-delay": 0,
            "push-to-talk": false,
            "push-to-talk-delay": 0,
            "settings": {
                "close_when_inactive": false,
                "input": "http://localhost:4816/media/video/observeress-demo-intro-video.mp4",
                "is_local_file": false,
                "seekable": true
            },
            "sync": 0,
            "versioned_id": "ffmpeg_source",
            "volume": 1.0
        },
        {
            "balance": 0.5,
            "deinterlace_field_order": 0,
            "deinterlace_mode": 0,
            "enabled": true,
            "flags": 0,
            "hotkeys": {
                "OBSBasic.SelectScene": [],
                "libobs.hide_scene_item.Media Source - Intro Video": [],
                "libobs.show_scene_item.Media Source - Intro Video": []
            },
            "id": "scene",
            "mixers": 0,
            "monitoring_type": 0,
            "muted": false,
            "name": "Intro Video",
            "prev_ver": 452984833,
            "private_settings": {},
            "push-to-mute": false,
            "push-to-mute-delay": 0,
            "push-to-talk": false,
            "push-to-talk-delay": 0,
            "settings": {
                "custom_size": false,
                "id_counter": 1,
                "items": [
                    {
                        "align": 5,
                        "bounds": {
                            "x": 0.0,
                            "y": 0.0
                        },
                        "bounds_align": 0,
                        "bounds_type": 0,
                        "crop_bottom": 0,
                        "crop_left": 0,
                        "crop_right": 0,
                        "crop_top": 0,
                        "group_item_backup": false,
                        "hide_transition": {
                            "duration": 0
                        },
                        "id": 1,
                        "locked": false,
                        "name": "Media Source - Intro Video",
                        "pos": {
                            "x": 0.0,
                            "y": 0.0
                        },
                        "private_settings": {},
                        "rot": 0.0,
                        "scale": {
                            "x": 1.0,
                            "y": 1.0
                        },
                        "scale_filter": "disable",
                        "show_transition": {
                            "duration": 0
                        },
                        "visible": true
                    }
                ]
            },
            "sync": 0,
            "versioned_id": "scene",
            "volume": 1.0
        },
        {
            "balance": 0.5,
            "deinterlace_field_order": 0,
            "deinterlace_mode": 0,
            "enabled": true,
            "flags": 0,
            "hotkeys": {
                "libobs.mute": [],
                "libobs.push-to-mute": [],
                "libobs.push-to-talk": [],
                "libobs.unmute": []
            },
            "id": "browser_source",
            "mixers": 255,
            "monitoring_type": 2,
            "muted": false,
            "name": "Browser - Countdown",
            "prev_ver": 452984833,
            "private_settings": {},
            "push-to-mute": false,
            "push-to-mute-delay": 0,
            "push-to-talk": false,
            "push-to-talk-delay": 0,
            "settings": {
                "height": 1080,
                "reroute_audio": true,
                "restart_when_active": false,
                "shutdown": false,
                "url": "http://localhost:4816/display/observeress-show-demo/countdown.html",
                "width": 1920
            },
            "sync": 0,
            "versioned_id": "browser_source",
            "volume": 1.0
        },
        {
            "balance": 0.5,
            "deinterlace_field_order": 0,
            "deinterlace_mode": 0,
            "enabled": true,
            "flags": 0,
            "hotkeys": {
                "OBSBasic.SelectScene": []
            },
            "id": "scene",
            "mixers": 0,
            "monitoring_type": 0,
            "muted": false,
            "name": "Blank",
            "prev_ver": 452984833,
            "private_settings": {},
            "push-to-mute": false,
            "push-to-mute-delay": 0,
            "push-to-talk": false,
            "push-to-talk-delay": 0,
            "settings": {
                "custom_size": false,
                "id_counter": 0,
                "items": []
            },
            "sync": 0,
            "versioned_id": "scene",
            "volume": 1.0
        },
        {
            "balance": 0.5,
            "deinterlace_field_order": 0,
            "deinterlace_mode": 0,
            "enabled": true,
            "flags": 0,
            "hotkeys": {
                "libobs.mute": [],
                "libobs.push-to-mute": [],
                "libobs.push-to-talk": [],
                "libobs.unmute": []
            },
            "id": "browser_source",
            "mixers": 255,
            "monitoring_type": 0,
            "muted": false,
            "name": "Pretend Zoom Call",
            "prev_ver": 452984833,
            "private_settings": {},
            "push-to-mute": false,
            "push-to-mute-delay": 0,
            "push-to-talk": false,
            "push-to-talk-delay": 0,
            "settings": {
                "height": 720,
                "restart_when_active": false,
                "shutdown": true,
                "url": "http://localhost:4816/media/images/fakezoomcall.png",
                "width": 1280
            },
            "sync": 0,
            "versioned_id": "browser_source",
            "volume": 1.0
        },
        {
            "balance": 0.5,
            "deinterlace_field_order": 0,
            "deinterlace_mode": 0,
            "enabled": true,
            "flags": 0,
            "hotkeys": {
                "OBSBasic.SelectScene": [],
                "libobs.hide_scene_item.Zoom Call": [],
                "libobs.show_scene_item.Zoom Call": []
            },
            "id": "scene",
            "mixers": 0,
            "monitoring_type": 0,
            "muted": false,
            "name": "[internal] Zoom Call Raw",
            "prev_ver": 452984833,
            "private_settings": {},
            "push-to-mute": false,
            "push-to-mute-delay": 0,
            "push-to-talk": false,
            "push-to-talk-delay": 0,
            "settings": {
                "custom_size": false,
                "id_counter": 6,
                "items": [
                    {
                        "align": 5,
                        "bounds": {
                            "x": 0.0,
                            "y": 0.0
                        },
                        "bounds_align": 0,
                        "bounds_type": 0,
                        "crop_bottom": 0,
                        "crop_left": 0,
                        "crop_right": 0,
                        "crop_top": 0,
                        "group_item_backup": true,
                        "hide_transition": {
                            "duration": 0
                        },
                        "id": 2,
                        "locked": false,
                        "name": "Pretend Zoom Call",
                        "pos": {
                            "x": 0.0,
                            "y": 0.0
                        },
                        "private_settings": {},
                        "rot": 0.0,
                        "scale": {
                            "x": 1.5,
                            "y": 1.5
                        },
                        "scale_filter": "disable",
                        "show_transition": {
                            "duration": 0
                        },
                        "visible": true
                    },
                    {
                        "align": 5,
                        "bounds": {
                            "x": 0.0,
                            "y": 0.0
                        },
                        "bounds_align": 0,
                        "bounds_type": 0,
                        "crop_bottom": 0,
                        "crop_left": 0,
                        "crop_right": 0,
                        "crop_top": 0,
                        "group_item_backup": false,
                        "hide_transition": {
                            "duration": 0
                        },
                        "id": 6,
                        "locked": false,
                        "name": "Zoom Call",
                        "pos": {
                            "x": 0.0,
                            "y": 0.0
                        },
                        "private_settings": {},
                        "rot": 0.0,
                        "scale": {
                            "x": 1.0,
                            "y": 1.0
                        },
                        "scale_filter": "disable",
                        "show_transition": {
                            "duration": 0
                        },
                        "visible": true
                    }
                ]
            },
            "sync": 0,
            "versioned_id": "scene",
            "volume": 1.0
        },
        {
            "balance": 0.5,
            "deinterlace_field_order": 0,
            "deinterlace_mode": 0,
            "enabled": true,
            "flags": 0,
            "hotkeys": {
                "OBSBasic.SelectScene": [],
                "libobs.hide_scene_item.Browser - Countdown": [],
                "libobs.hide_scene_item.Browser - Video Background": [],
                "libobs.show_scene_item.Browser - Countdown": [],
                "libobs.show_scene_item.Browser - Video Background": []
            },
            "id": "scene",
            "mixers": 0,
            "monitoring_type": 0,
            "muted": false,
            "name": "Countdown",
            "prev_ver": 452984833,
            "private_settings": {},
            "push-to-mute": false,
            "push-to-mute-delay": 0,
            "push-to-talk": false,
            "push-to-talk-delay": 0,
            "settings": {
                "custom_size": false,
                "id_counter": 4,
                "items": [
                    {
                        "align": 5,
                        "bounds": {
                            "x": 0.0,
                            "y": 0.0
                        },
                        "bounds_align": 0,
                        "bounds_type": 0,
                        "crop_bottom": 0,
                        "crop_left": 0,
                        "crop_right": 0,
                        "crop_top": 0,
                        "group_item_backup": false,
                        "hide_transition": {
                            "duration": 0
                        },
                        "id": 1,
                        "locked": false,
                        "name": "Browser - Countdown",
                        "pos": {
                            "x": 0.0,
                            "y": 0.0
                        },
                        "private_settings": {},
                        "rot": 0.0,
                        "scale": {
                            "x": 1.0,
                            "y": 1.0
                        },
                        "scale_filter": "disable",
                        "show_transition": {
                            "duration": 0
                        },
                        "visible": true
                    },
                    {
                        "align": 5,
                        "bounds": {
                            "x": 0.0,
                            "y": 0.0
                        },
                        "bounds_align": 0,
                        "bounds_type": 0,
                        "crop_bottom": 0,
                        "crop_left": 0,
                        "crop_right": 0,
                        "crop_top": 0,
                        "group_item_backup": false,
                        "hide_transition": {
                            "duration": 0
                        },
                        "id": 4,
                        "locked": false,
                        "name": "Browser - Video Background",
                        "pos": {
                            "x": 0.0,
                            "y": 0.0
                        },
                        "private_settings": {},
                        "rot": 0.0,
                        "scale": {
                            "x": 1.0,
                            "y": 1.0
                        },
                        "scale_filter": "disable",
                        "show_transition": {
                            "duration": 0
                        },
                        "visible": true
                    }
                ]
            },
            "sync": 0,
            "versioned_id": "scene",
            "volume": 1.0
        },
        {
            "balance": 0.5,
            "deinterlace_field_order": 0,
            "deinterlace_mode": 0,
            "enabled": true,
            "flags": 0,
            "hotkeys": {
                "OBSBasic.SelectScene": [],
                "libobs.hide_scene_item.Browser - Main Footer": [],
                "libobs.hide_scene_item.Browser - Media Player": [],
                "libobs.hide_scene_item.Browser - Video Background": [],
                "libobs.hide_scene_item.Zoom Audio": [],
                "libobs.hide_scene_item.Zoom Call Side FX": [],
                "libobs.show_scene_item.Browser - Main Footer": [],
                "libobs.show_scene_item.Browser - Media Player": [],
                "libobs.show_scene_item.Browser - Video Background": [],
                "libobs.show_scene_item.Zoom Audio": [],
                "libobs.show_scene_item.Zoom Call Side FX": []
            },
            "id": "scene",
            "mixers": 0,
            "monitoring_type": 0,
            "muted": false,
            "name": "Media Player",
            "prev_ver": 452984833,
            "private_settings": {},
            "push-to-mute": false,
            "push-to-mute-delay": 0,
            "push-to-talk": false,
            "push-to-talk-delay": 0,
            "settings": {
                "custom_size": false,
                "id_counter": 8,
                "items": [
                    {
                        "align": 5,
                        "bounds": {
                            "x": 0.0,
                            "y": 0.0
                        },
                        "bounds_align": 0,
                        "bounds_type": 0,
                        "crop_bottom": 0,
                        "crop_left": 0,
                        "crop_right": 0,
                        "crop_top": 0,
                        "group_item_backup": false,
                        "hide_transition": {
                            "duration": 0
                        },
                        "id": 1,
                        "locked": false,
                        "name": "Browser - Video Background",
                        "pos": {
                            "x": 0.0,
                            "y": 0.0
                        },
                        "private_settings": {},
                        "rot": 0.0,
                        "scale": {
                            "x": 1.0,
                            "y": 1.0
                        },
                        "scale_filter": "disable",
                        "show_transition": {
                            "duration": 0
                        },
                        "visible": true
                    },
                    {
                        "align": 5,
                        "bounds": {
                            "x": 0.0,
                            "y": 0.0
                        },
                        "bounds_align": 0,
                        "bounds_type": 0,
                        "crop_bottom": 0,
                        "crop_left": 0,
                        "crop_right": 0,
                        "crop_top": 0,
                        "group_item_backup": false,
                        "hide_transition": {
                            "duration": 0
                        },
                        "id": 3,
                        "locked": false,
                        "name": "Browser - Main Footer",
                        "pos": {
                            "x": 0.0,
                            "y": 0.0
                        },
                        "private_settings": {},
                        "rot": 0.0,
                        "scale": {
                            "x": 1.0,
                            "y": 1.0
                        },
                        "scale_filter": "disable",
                        "show_transition": {
                            "duration": 0
                        },
                        "visible": true
                    },
                    {
                        "align": 5,
                        "bounds": {
                            "x": 0.0,
                            "y": 0.0
                        },
                        "bounds_align": 0,
                        "bounds_type": 0,
                        "crop_bottom": 0,
                        "crop_left": 0,
                        "crop_right": 969,
                        "crop_top": 0,
                        "group_item_backup": true,
                        "hide_transition": {
                            "duration": 0
                        },
                        "id": 2,
                        "locked": false,
                        "name": "[internal] Zoom Call Raw",
                        "pos": {
                            "x": 1519.0,
                            "y": 434.0
                        },
                        "private_settings": {},
                        "rot": 0.0,
                        "scale": {
                            "x": 0.37329128384590149,
                            "y": 0.37314814329147339
                        },
                        "scale_filter": "disable",
                        "show_transition": {
                            "duration": 0
                        },
                        "visible": true
                    },
                    {
                        "align": 5,
                        "bounds": {
                            "x": 0.0,
                            "y": 0.0
                        },
                        "bounds_align": 0,
                        "bounds_type": 0,
                        "crop_bottom": 0,
                        "crop_left": 954,
                        "crop_right": 0,
                        "crop_top": 0,
                        "group_item_backup": true,
                        "hide_transition": {
                            "duration": 0
                        },
                        "id": 7,
                        "locked": false,
                        "name": "[internal] Zoom Call Raw",
                        "pos": {
                            "x": 1517.0,
                            "y": 37.0
                        },
                        "private_settings": {},
                        "rot": 0.0,
                        "scale": {
                            "x": 0.36749482154846191,
                            "y": 0.36759260296821594
                        },
                        "scale_filter": "disable",
                        "show_transition": {
                            "duration": 0
                        },
                        "visible": true
                    },
                    {
                        "align": 5,
                        "bounds": {
                            "x": 0.0,
                            "y": 0.0
                        },
                        "bounds_align": 0,
                        "bounds_type": 0,
                        "crop_bottom": 0,
                        "crop_left": 0,
                        "crop_right": 0,
                        "crop_top": 0,
                        "group_item_backup": false,
                        "hide_transition": {
                            "duration": 0
                        },
                        "id": 8,
                        "locked": false,
                        "name": "Zoom Call Side FX",
                        "pos": {
                            "x": 1517.0,
                            "y": 37.0
                        },
                        "private_settings": {},
                        "rot": 0.0,
                        "scale": {
                            "x": 1.0,
                            "y": 1.0
                        },
                        "scale_filter": "disable",
                        "show_transition": {
                            "duration": 0
                        },
                        "visible": true
                    },
                    {
                        "align": 5,
                        "bounds": {
                            "x": 0.0,
                            "y": 0.0
                        },
                        "bounds_align": 0,
                        "bounds_type": 0,
                        "crop_bottom": 219,
                        "crop_left": 0,
                        "crop_right": 0,
                        "crop_top": 0,
                        "group_item_backup": false,
                        "hide_transition": {
                            "duration": 0
                        },
                        "id": 6,
                        "locked": false,
                        "name": "Browser - Media Player",
                        "pos": {
                            "x": 0.0,
                            "y": 0.0
                        },
                        "private_settings": {},
                        "rot": 0.0,
                        "scale": {
                            "x": 1.0,
                            "y": 1.0
                        },
                        "scale_filter": "disable",
                        "show_transition": {
                            "duration": 0
                        },
                        "visible": true
                    },
                    {
                        "align": 5,
                        "bounds": {
                            "x": 0.0,
                            "y": 0.0
                        },
                        "bounds_align": 0,
                        "bounds_type": 0,
                        "crop_bottom": 0,
                        "crop_left": 0,
                        "crop_right": 0,
                        "crop_top": 0,
                        "group_item_backup": false,
                        "hide_transition": {
                            "duration": 0
                        },
                        "id": 4,
                        "locked": false,
                        "name": "Zoom Audio",
                        "pos": {
                            "x": 0.0,
                            "y": 0.0
                        },
                        "private_settings": {},
                        "rot": 0.0,
                        "scale": {
                            "x": 1.0,
                            "y": 1.0
                        },
                        "scale_filter": "disable",
                        "show_transition": {
                            "duration": 0
                        },
                        "visible": false
                    }
                ]
            },
            "sync": 0,
            "versioned_id": "scene",
            "volume": 1.0
        },
        {
            "balance": 0.5,
            "deinterlace_field_order": 0,
            "deinterlace_mode": 0,
            "enabled": true,
            "flags": 0,
            "hotkeys": {
                "libobs.mute": [],
                "libobs.push-to-mute": [],
                "libobs.push-to-talk": [],
                "libobs.unmute": []
            },
            "id": "browser_source",
            "mixers": 255,
            "monitoring_type": 2,
            "muted": false,
            "name": "Browser - Main Zoom Surround",
            "prev_ver": 452984833,
            "private_settings": {},
            "push-to-mute": false,
            "push-to-mute-delay": 0,
            "push-to-talk": false,
            "push-to-talk-delay": 0,
            "settings": {
                "css": "body { background-color: rgba(0, 0, 0, 0); margin: 0px auto; overflow: hidden; }",
                "fps": 30,
                "fps_custom": false,
                "height": 1080,
                "reroute_audio": true,
                "restart_when_active": true,
                "shutdown": false,
                "undo_sname": "Browser - Main Zoom Surround",
                "url": "http://localhost:4816/display/observeress-show-demo/main-zoom-surround.html",
                "width": 1920
            },
            "sync": 0,
            "versioned_id": "browser_source",
            "volume": 1.0
        },
        {
            "balance": 0.5,
            "deinterlace_field_order": 0,
            "deinterlace_mode": 0,
            "enabled": true,
            "flags": 0,
            "hotkeys": {
                "libobs.mute": [],
                "libobs.push-to-mute": [],
                "libobs.push-to-talk": [],
                "libobs.unmute": []
            },
            "id": "browser_source",
            "mixers": 255,
            "monitoring_type": 2,
            "muted": false,
            "name": "Browser - Media Player",
            "prev_ver": 452984833,
            "private_settings": {},
            "push-to-mute": false,
            "push-to-mute-delay": 0,
            "push-to-talk": false,
            "push-to-talk-delay": 0,
            "settings": {
                "fps": 25,
                "fps_custom": true,
                "height": 1080,
                "reroute_audio": true,
                "restart_when_active": true,
                "shutdown": true,
                "url": "http://localhost:4816/display/observeress-show-demo/media-player.html",
                "width": 1920
            },
            "sync": 0,
            "versioned_id": "browser_source",
            "volume": 1.0
        }
    ],
    "transition_duration": 800,
    "transitions": [
        {
            "id": "wipe_transition",
            "name": "Luma Wipe",
            "settings": {}
        },
        {
            "id": "swipe_transition",
            "name": "Swipe",
            "settings": {
                "direction": "left",
                "swipe_in": false
            }
        }
    ]
}